{
  "id": "stage",
  "type": "SharedSlice",
  "name": "Stage",
  "description": "Stage",
  "variations": [
    {
      "id": "default",
      "name": "Default",
      "docURL": "...",
      "version": "sktwi1xtmkfgx8626",
      "description": "Stage",
      "primary": {
        "content": {
          "type": "StructuredText",
          "config": {
            "label": "Content",
            "placeholder": "",
            "allowTargetBlank": true,
            "single": "paragraph,preformatted,heading1,heading2,heading3,heading4,heading5,heading6,strong,em,hyperlink,image,embed,list-item,o-list-item,rtl"
          }
        },
        "asset": {
          "type": "Select",
          "config": {
            "label": "Asset",
            "placeholder": "",
            "options": [
              "video",
              "image"
            ]
          }
        },
        "videoLink": {
          "type": "Link",
          "config": {
            "label": "Video Link",
            "placeholder": "",
            "select": null
          }
        },
        "image": {
          "type": "Image",
          "config": {
            "label": "Image",
            "constraint": {},
            "thumbnails": []
          }
        },
        "layout": {
          "type": "Select",
          "config": {
            "label": "Layout",
            "placeholder": "",
            "options": [
              "fullWidth",
              "splitView"
            ]
          }
        },
        "link": {
          "type": "Link",
          "config": {
            "label": "Link",
            "placeholder": "",
            "select": null
          }
        },
        "linkLabel": {
          "type": "Text",
          "config": {
            "label": "Link Label",
            "placeholder": ""
          }
        }
      },
      "items": {},
      "imageUrl": "https://images.prismic.io/slice-machine/621a5ec4-0387-4bc5-9860-2dd46cbc07cd_default_ss.png?auto=compress,format"
    }
  ]
}